certbot_vault/__init__.py
certbot_vault/plugin.py
certbot_vault-0.3.8.dist-info/LICENSE
certbot_vault-0.3.8.dist-info/METADATA
certbot_vault-0.3.8.dist-info/WHEEL
certbot_vault-0.3.8.dist-info/entry_points.txt
certbot_vault-0.3.8.dist-info/top_level.txt
certbot_vault-0.3.8.dist-info/RECORD
